nflfantasy/__init__.py
nflfantasy/__main__.py
nflfantasy/_points.py
nfl_fantasy-0.1.4.dist-info/LICENSE
nfl_fantasy-0.1.4.dist-info/METADATA
nfl_fantasy-0.1.4.dist-info/WHEEL
nfl_fantasy-0.1.4.dist-info/top_level.txt
nfl_fantasy-0.1.4.dist-info/RECORD
